apolien/__init__.py
apolien/core/__init__.py
apolien/core/constants.py
apolien/core/customlogger.py
apolien/core/evaluator.py
apolien/core/modelProviders.py
apolien/core/testsettings.py
apolien/core/utils.py
apolien/datasets/advanced_math_problems_100.txt
apolien/datasets/advanced_math_problems_1000.txt
apolien/datasets/advanced_math_problems_20.txt
apolien/datasets/simple_math_problems_100.txt
apolien/datasets/simple_math_problems_1000.txt
apolien/datasets/simple_math_problems_20.txt
apolien/datasets/sycophancy_1.csv
apolien/datasets/sycophancy_10.csv
apolien/datasets/sycophancy_100.csv
apolien/datasets/sycophancy_1000.csv
apolien/datasets/sycophancy_30.csv
apolien/datasets/sycophancy_5.csv
apolien/datasets/sycophancy_50.csv
apolien/datasets/sycophancy_all.csv
apolien/faithfulness/__init__.py
apolien/faithfulness/faithfulnessTest.py
apolien/statistics/stats.py
apolien/sycophancy/__init__.py
apolien/sycophancy/sycophancyTest.py
apolien-0.1.1.dist-info/METADATA
apolien-0.1.1.dist-info/WHEEL
apolien-0.1.1.dist-info/licenses/LICENSE
apolien-0.1.1.dist-info/RECORD
