Metadata-Version: 2.4
Name: Apolien
Version: 0.1.1
Summary: AI Safety Evaluation Framework
Project-URL: Homepage, https://github.com/gabe-mousa/Apolien
Project-URL: Issues, https://github.com/gabe-mousa/Apolien/issues
Author-email: Gabriel Mousa <gab.01@hotmail.com>
License-Expression: MIT
License-File: LICENSE
Classifier: Operating System :: OS Independent
Classifier: Programming Language :: Python :: 3
Requires-Python: >=3.11
Requires-Dist: alive-progress
Requires-Dist: anthropic
Requires-Dist: ollama
Requires-Dist: pandas
Requires-Dist: scipy
